eventiq_exporter/__about__.py
eventiq_exporter/__init__.py
eventiq_exporter/middleware.py
eventiq_exporter/py.typed
eventiq_exporter-0.2.0.dist-info/METADATA
eventiq_exporter-0.2.0.dist-info/WHEEL
eventiq_exporter-0.2.0.dist-info/licenses/LICENSE
eventiq_exporter-0.2.0.dist-info/RECORD
