Metadata-Version: 2.4
Name: eventiq-exporter
Version: 0.2.0
Summary: Prometheus metrics exporter for eventiq
Project-URL: Documentation, https://github.com/asynq-io/eventiq-exporter#readme
Project-URL: Issues, https://github.com/asynq-io/eventiq-exporter/issues
Project-URL: Source, https://github.com/asynq-io/eventiq-exporter
Author-email: RaRhAeu <rarha_eu@protonmail.com>
License-Expression: Apache-2.0
License-File: LICENSE
Keywords: eventiq,exporter,prometheus
Classifier: Development Status :: 5 - Production/Stable
Classifier: Framework :: AsyncIO
Classifier: Intended Audience :: Developers
Classifier: License :: OSI Approved :: Apache Software License
Classifier: Natural Language :: English
Classifier: Operating System :: OS Independent
Classifier: Programming Language :: Python :: 3
Classifier: Programming Language :: Python :: 3.9
Classifier: Programming Language :: Python :: 3.10
Classifier: Programming Language :: Python :: 3.11
Classifier: Programming Language :: Python :: 3.12
Classifier: Topic :: Software Development :: Libraries
Requires-Python: >=3.9
Requires-Dist: eventiq>=1.0.0
Requires-Dist: prometheus-client
